viam/__init__.py
viam/errors.py
viam/logging.py
viam/operations.py
viam/py.typed
viam/sessions_client.py
viam/streams.py
viam/utils.py
viam/version_metadata.py
viam/app/__init__.py
viam/app/_logs.py
viam/app/app_client.py
viam/app/billing_client.py
viam/app/data_client.py
viam/app/ml_training_client.py
viam/app/provisioning_client.py
viam/app/viam_client.py
viam/components/__init__.py
viam/components/component_base.py
viam/components/arm/__init__.py
viam/components/arm/arm.py
viam/components/arm/client.py
viam/components/arm/service.py
viam/components/audio_in/__init__.py
viam/components/audio_in/audio_in.py
viam/components/audio_in/client.py
viam/components/audio_in/service.py
viam/components/audio_out/__init__.py
viam/components/audio_out/audio_out.py
viam/components/audio_out/client.py
viam/components/audio_out/service.py
viam/components/base/__init__.py
viam/components/base/base.py
viam/components/base/client.py
viam/components/base/service.py
viam/components/board/__init__.py
viam/components/board/board.py
viam/components/board/client.py
viam/components/board/service.py
viam/components/button/__init__.py
viam/components/button/button.py
viam/components/button/client.py
viam/components/button/service.py
viam/components/camera/__init__.py
viam/components/camera/camera.py
viam/components/camera/client.py
viam/components/camera/service.py
viam/components/encoder/__init__.py
viam/components/encoder/client.py
viam/components/encoder/encoder.py
viam/components/encoder/service.py
viam/components/gantry/__init__.py
viam/components/gantry/client.py
viam/components/gantry/gantry.py
viam/components/gantry/service.py
viam/components/generic/__init__.py
viam/components/generic/client.py
viam/components/generic/generic.py
viam/components/generic/service.py
viam/components/gripper/__init__.py
viam/components/gripper/client.py
viam/components/gripper/gripper.py
viam/components/gripper/service.py
viam/components/input/__init__.py
viam/components/input/client.py
viam_sdk-0.67.0.dist-info/METADATA
viam_sdk-0.67.0.dist-info/WHEEL
viam_sdk-0.67.0.dist-info/licenses/LICENSE
viam_sdk-0.67.0.dist-info/RECORD
