Metadata-Version: 2.4
Name: viam-sdk
Version: 0.67.0
Summary: Viam Robotics Python SDK
Project-URL: Homepage, https://www.viam.com
Project-URL: Documentation, https://python.viam.dev
Project-URL: Repository, https://github.com/viamrobotics/viam-python-sdk
Author-email: Naveed Jooma <naveed@viam.com>
License-Expression: Apache-2.0
License-File: LICENSE
Requires-Python: >=3.8.1
Requires-Dist: googleapis-common-protos>=1.65.0
Requires-Dist: grpclib>=0.4.7
Requires-Dist: protobuf==5.29.5
Requires-Dist: pymongo>=4.10.1
Requires-Dist: typing-extensions>=4.12.2
Provides-Extra: mlmodel
Requires-Dist: numpy; extra == 'mlmodel'
